droidtools/__init__.py
droidtools/bootimg.py
droidtools/ext4fs.cpython-310-darwin.so
droidtools/ext4fs_utils.py
droidtools/minicpio.py
droidtools/mkbootimg.py
droidtools/test_ext4fs_utils.py
droidtools/unlokibootimg.py
droidtools/unpackbootimg.py
python_ext4fs-0.1a10.dist-info/LICENSE
python_ext4fs-0.1a10.dist-info/METADATA
python_ext4fs-0.1a10.dist-info/WHEEL
python_ext4fs-0.1a10.dist-info/top_level.txt
python_ext4fs-0.1a10.dist-info/RECORD
