Metadata-Version: 2.1
Name: python-ext4fs
Version: 0.1a10
Summary: Some android tools
Author: Tarek Galal
Author-email: tare2.galal@gmail.com
License: GPLv3 License
Platform: any
Classifier: Programming Language :: Python
Classifier: Development Status :: 3 - Alpha
Classifier: Natural Language :: English
Classifier: Intended Audience :: Developers
Classifier: License :: OSI Approved :: GNU General Public License v3 or later (GPLv3+)
Classifier: Operating System :: OS Independent
Classifier: Topic :: Software Development :: Libraries :: Python Modules
License-File: LICENSE
